{
    "garlium.garlicpool.org": {
        "pruning": "-",
        "s": "50002",
        "t": "50001",
        "version": "1.1"
    },
    "roflmining.com": {
        "pruning": "-",
        "s": "50002",
        "t": "50001",
        "version": "1.1"
    },
    "tuxprint.com": {
        "pruning": "-",
        "s": "50002",
        "t": "50001",
        "version": "1.1"
    },
    "garlium.rshaw.space": {
        "pruning": "-",
        "s": "50002",
        "t": "50001",
        "version": "1.2"
    },
    "electrum.garli.co.in": {
        "pruning": "-",
        "s": "50002",
        "t": "50001",
        "version": "1.1"
    }
}